elasticsearch7/__init__.py
elasticsearch7/__init__.pyi
elasticsearch7/_version.py
elasticsearch7/compat.py
elasticsearch7/compat.pyi
elasticsearch7/connection_pool.py
elasticsearch7/connection_pool.pyi
elasticsearch7/exceptions.py
elasticsearch7/exceptions.pyi
elasticsearch7/py.typed
elasticsearch7/serializer.py
elasticsearch7/serializer.pyi
elasticsearch7/transport.py
elasticsearch7/transport.pyi
elasticsearch7/utils.py
elasticsearch7/utils.pyi
elasticsearch7/_async/__init__.py
elasticsearch7/_async/_extra_imports.py
elasticsearch7/_async/compat.py
elasticsearch7/_async/compat.pyi
elasticsearch7/_async/helpers.py
elasticsearch7/_async/helpers.pyi
elasticsearch7/_async/http_aiohttp.py
elasticsearch7/_async/http_aiohttp.pyi
elasticsearch7/_async/transport.py
elasticsearch7/_async/transport.pyi
elasticsearch7/_async/client/__init__.py
elasticsearch7/_async/client/__init__.pyi
elasticsearch7/_async/client/async_search.py
elasticsearch7/_async/client/async_search.pyi
elasticsearch7/_async/client/autoscaling.py
elasticsearch7/_async/client/autoscaling.pyi
elasticsearch7/_async/client/cat.py
elasticsearch7/_async/client/cat.pyi
elasticsearch7/_async/client/ccr.py
elasticsearch7/_async/client/ccr.pyi
elasticsearch7/_async/client/cluster.py
elasticsearch7/_async/client/cluster.pyi
elasticsearch7/_async/client/dangling_indices.py
elasticsearch7/_async/client/dangling_indices.pyi
elasticsearch7/_async/client/data_frame.py
elasticsearch7/_async/client/data_frame.pyi
elasticsearch7/_async/client/deprecation.py
elasticsearch7/_async/client/deprecation.pyi
elasticsearch7/_async/client/enrich.py
elasticsearch7/_async/client/enrich.pyi
elasticsearch7/_async/client/eql.py
elasticsearch7/_async/client/eql.pyi
elasticsearch7/_async/client/features.py
elasticsearch7/_async/client/features.pyi
elasticsearch7/_async/client/fleet.py
elasticsearch7/_async/client/fleet.pyi
elasticsearch7/_async/client/graph.py
elasticsearch7/_async/client/graph.pyi
elasticsearch7/_async/client/ilm.py
elasticsearch7-7.17.12.dist-info/LICENSE
elasticsearch7-7.17.12.dist-info/METADATA
elasticsearch7-7.17.12.dist-info/NOTICE
elasticsearch7-7.17.12.dist-info/WHEEL
elasticsearch7-7.17.12.dist-info/top_level.txt
elasticsearch7-7.17.12.dist-info/RECORD
